{
    "$schema":  "https://json-schema.org/draft-07/schema#",
    "title":  "Ghost Helm Chart Values",
    "description":  "Values for the Ghost Helm chart - modern publishing platform and headless CMS with MySQL backend",
    "type":  "object",
    "additionalProperties":  true,
    "properties":  {
                       "nameOverride":  {
                                            "type":  "string",
                                            "default":  ""
                                        },
                       "fullnameOverride":  {
                                                "type":  "string",
                                                "default":  ""
                                            },
                       "commonLabels":  {
                                            "type":  "object"
                                        },
                       "image":  {
                                     "type":  "object",
                                     "properties":  {
                                                        "repository":  {
                                                                           "type":  "string",
                                                                           "default":  "docker.io/library/ghost"
                                                                       },
                                                        "tag":  {
                                                                    "type":  "string",
                                                                    "default":  "6.37.1"
                                                                },
                                                        "pullPolicy":  {
                                                                           "type":  "string",
                                                                           "enum":  [
                                                                                        "Always",
                                                                                        "IfNotPresent",
                                                                                        "Never"
                                                                                    ],
                                                                           "default":  "IfNotPresent"
                                                                       }
                                                    }
                                 },
                       "imagePullSecrets":  {
                                                "type":  "array",
                                                "items":  {
                                                              "type":  "object"
                                                          }
                                            },
                       "ghost":  {
                                     "type":  "object",
                                     "description":  "Ghost application configuration",
                                     "properties":  {
                                                        "url":  {
                                                                    "type":  "string",
                                                                    "description":  "Public URL of the Ghost instance",
                                                                    "default":  ""
                                                                },
                                                        "extraEnv":  {
                                                                         "type":  "array",
                                                                         "items":  {
                                                                                       "type":  "object"
                                                                                   }
                                                                     }
                                                    }
                                 },
                       "database":  {
                                        "type":  "object",
                                        "description":  "External MySQL database configuration",
                                        "properties":  {
                                                           "external":  {
                                                                            "type":  "object"
                                                                        }
                                                       }
                                    },
                       "persistence":  {
                                           "type":  "object",
                                           "properties":  {
                                                              "enabled":  {
                                                                              "type":  "boolean",
                                                                              "default":  true
                                                                          },
                                                              "size":  {
                                                                           "type":  "string",
                                                                           "default":  "10Gi"
                                                                       },
                                                              "storageClass":  {
                                                                                   "type":  "string",
                                                                                   "default":  ""
                                                                               },
                                                              "accessModes":  {
                                                                                  "type":  "array",
                                                                                  "items":  {
                                                                                                "type":  "string"
                                                                                            }
                                                                              },
                                                              "existingClaim":  {
                                                                                    "type":  "string",
                                                                                    "default":  ""
                                                                                }
                                                          }
                                       },
                       "backup":  {
                                      "type":  "object"
                                  },
                       "serviceAccount":  {
                                              "type":  "object",
                                              "properties":  {
                                                                 "create":  {
                                                                                "type":  "boolean",
                                                                                "default":  false
                                                                            },
                                                                 "name":  {
                                                                              "type":  "string",
                                                                              "default":  ""
                                                                          },
                                                                 "annotations":  {
                                                                                     "type":  "object"
                                                                                 }
                                                             }
                                          },
                       "service":  {
                                       "type":  "object",
                                       "properties":  {
                                                          "type":  {
                                                                       "type":  "string",
                                                                       "enum":  [
                                                                                    "ClusterIP",
                                                                                    "NodePort",
                                                                                    "LoadBalancer"
                                                                                ],
                                                                       "default":  "ClusterIP"
                                                                   },
                                                          "port":  {
                                                                       "type":  "integer",
                                                                       "default":  80
                                                                   },
                                                          "annotations":  {
                                                                              "type":  "object"
                                                                          },
                                                          "ipFamilyPolicy":  {
                                                                                 "type":  ["string", "null"],
                                                                                 "description":  "Dual-stack ipFamilyPolicy (GR-058)",
                                                                                 "enum":  [null, "SingleStack", "PreferDualStack", "RequireDualStack"]
                                                                             },
                                                          "ipFamilies":  {
                                                                             "type":  "array",
                                                                             "description":  "Dual-stack ipFamilies (GR-058)",
                                                                             "items":  {
                                                                                           "type":  "string",
                                                                                           "enum":  ["IPv4", "IPv6"]
                                                                                       },
                                                                             "maxItems":  2
                                                                         }
                                                      }
                                   },
                       "ingress":  {
                                       "type":  "object",
                                       "properties":  {
                                                          "enabled":  {
                                                                          "type":  "boolean",
                                                                          "default":  false
                                                                      },
                                                          "ingressClassName":  {
                                                                                   "type":  "string",
                                                                                   "default":  "traefik"
                                                                               },
                                                          "annotations":  {
                                                                              "type":  "object"
                                                                          },
                                                          "hosts":  {
                                                                        "type":  "array",
                                                                        "items":  {
                                                                                      "type":  "object"
                                                                                  }
                                                                    },
                                                          "tls":  {
                                                                      "type":  "array",
                                                                      "items":  {
                                                                                    "type":  "object"
                                                                                }
                                                                  }
                                                      }
                                   },
                       "probes":  {
                                      "type":  "object"
                                  },
                       "resources":  {
                                         "type":  "object"
                                     },
                       "podSecurityContext":  {
                                                  "type":  "object"
                                              },
                       "securityContext":  {
                                               "type":  "object"
                                           },
                       "nodeSelector":  {
                                            "type":  "object"
                                        },
                       "tolerations":  {
                                           "type":  "array",
                                           "items":  {
                                                         "type":  "object"
                                                     }
                                       },
                       "affinity":  {
                                        "type":  "object"
                                    },
                       "topologySpreadConstraints":  {
                                                         "type":  "array",
                                                         "items":  {
                                                                       "type":  "object"
                                                                   }
                                                     },
                       "priorityClassName":  {
                                                 "type":  "string",
                                                 "default":  ""
                                             },
                       "terminationGracePeriodSeconds":  {
                                                             "type":  "integer",
                                                             "default":  30
                                                         },
                       "podLabels":  {
                                         "type":  "object"
                                     },
                       "podAnnotations":  {
                                              "type":  "object"
                                          },
                       "extraVolumes":  {
                                            "type":  "array",
                                            "items":  {
                                                          "type":  "object"
                                                      }
                                        },
                       "extraVolumeMounts":  {
                                                 "type":  "array",
                                                 "items":  {
                                                               "type":  "object"
                                                           }
                                             },
                       "extraManifests":  {
                                              "type":  "array",
                                              "items":  {
                                                            "type":  "object"
                                                        }
                                          },
                       "mysql":  {
                                     "type":  "object",
                                     "properties":  {
                                                        "enabled":  {
                                                                        "type":  "boolean",
                                                                        "default":  true
                                                                    }
                                                    }
                                 },
                       "gateway":  {
                                       "type":  "object",
                                       "description":  "Gateway API (HTTPRoute) configuration.",
                                       "properties": {
                                           "enabled": { "type": "boolean", "default": false },
                                           "annotations": { "type": "object" },
                                           "parentRefs": { "type": "array", "items": { "type": "object" } },
                                           "hostnames": { "type": "array", "items": { "type": "string" } },
                                           "path": { "type": "string", "default": "/" },
                                           "pathType": { "type": "string", "enum": ["PathPrefix", "Exact", "RegularExpression"], "default": "PathPrefix" }
                                       }
                                   },
                       "externalSecrets":  {
                                               "type":  "object",
                                               "description":  "ExternalSecrets Operator configuration.",
                                               "properties": {
                                                   "enabled": { "type": "boolean", "default": false },
                                                   "apiVersion": { "type": "string" },
                                                   "refreshInterval": { "type": "string" },
                                                   "secretStoreRef": { "type": "object" },
                                                   "target": { "type": "object" },
                                                   "data": { "type": "array" }
                                               }
                                           }
                   }
}
